{
  "dsn": {
    "form-field-description": {
      "font-family": {
        "value": "{dsn.text.font-family.default}",
        "type": "fontFamily",
        "comment": "Form field description font family"
      },
      "font-size": {
        "value": "{dsn.text.font-size.md}",
        "type": "fontSize",
        "comment": "Form field description font size"
      },
      "font-weight": {
        "value": "{dsn.text.font-weight.default}",
        "type": "fontWeight",
        "comment": "Form field description font weight"
      },
      "line-height": {
        "value": "{dsn.text.line-height.md}",
        "type": "lineHeight",
        "comment": "Form field description line height"
      },
      "color": {
        "value": "{dsn.color.neutral.color-subtle}",
        "type": "color",
        "comment": "Form field description text color"
      },
      "margin-block-end": {
        "value": "{dsn.space.block.md}",
        "type": "dimension",
        "comment": "Space below description before form control"
      }
    }
  }
}
